addons/__init__.py
addons/mod3.py
filter_pkg-0.1.0.dist-info/LICENSE
filter_pkg-0.1.0.dist-info/METADATA
filter_pkg-0.1.0.dist-info/WHEEL
filter_pkg-0.1.0.dist-info/top_level.txt
filter_pkg-0.1.0.dist-info/RECORD
