Metadata-Version: 2.1
Name: filter-pkg
Version: 0.1.0
Summary: This is a package created for random generating JSON, Numbers and passwords
Home-page: https://github.com/varunkatiyar819/filter_pkg
Author: Varun Katiyar
Author-email: varunkatiyar819@gmail.com
License: UNKNOWN
Platform: UNKNOWN
License-File: LICENSE
Requires-Dist: JSON
Requires-Dist: random
Requires-Dist: string
